reflex_mathjax/__init__.py
reflex_mathjax/mathjax.py
reflex_mathjax-0.0.4.dist-info/METADATA
reflex_mathjax-0.0.4.dist-info/WHEEL
reflex_mathjax-0.0.4.dist-info/RECORD
